LICENSE
MANIFEST.in
README
requirements.txt
setup.py
fbprophet/__init__.py
fbprophet/diagnostics.py
fbprophet/forecaster.py
fbprophet/hdays.py
fbprophet/make_holidays.py
fbprophet/models.py
fbprophet/plot.py
fbprophet.egg-info/PKG-INFO
fbprophet.egg-info/PKG-INFO~
fbprophet.egg-info/SOURCES.txt
fbprophet.egg-info/dependency_links.txt
fbprophet.egg-info/not-zip-safe
fbprophet.egg-info/requires.txt
fbprophet.egg-info/top_level.txt
fbprophet/tests/__init__.py
fbprophet/tests/data.csv
fbprophet/tests/data2.csv
fbprophet/tests/test_diagnostics.py
fbprophet/tests/test_prophet.py
stan/unix/prophet.stan
stan/win/prophet.stan