Metadata-Version: 1.0
Name: fbprophet
Version: 0.4
Summary: Automatic Forecasting Procedure
Home-page: https://facebook.github.io/prophet/
Author: Sean J. Taylor <sjt@fb.com>, Ben Letham <bletham@fb.com>
Author-email: sjt@fb.com
License: BSD
Platform: UNKNOWN
